{
    "name": "flights_113388d8e18b",
    "displayName": "Filter",
    "type": "FILTER",
    "dependencies": [
        {
            "type": "dataframe",
            "id": "flights_Source1"
        }
    ],
    "belongsTo": {
        "type": "dataframe",
        "id": "flights"
    },
    "props": {},
    "transform": {
        "type": "",
        "props": {},
        "script": "filter(carrier == \"AA\")",
        "command": {
            "name": "filter",
            "conditions": [
                {
                    "formType": "column",
                    "column": {
                        "name": "carrier",
                        "type": "character"
                    },
                    "valueType": "specificDate",
                    "operator": "equalTo",
                    "val": "AA"
                }
            ],
            "logicalOperation": "and"
        }
    },
    "timestamp": "2016-09-28T21:37:39.606Z",
    "filename": "flights_113388d8e18b.json"
}